minigenjax/__init__.py
minigenjax/minigenjax.py
minigenjax/pytree.py
minigenjax/test_minigenjax.py
minigenjax-0.1.0.dist-info/METADATA
minigenjax-0.1.0.dist-info/WHEEL
minigenjax-0.1.0.dist-info/RECORD
